langchain_fused_model/__init__.py
langchain_fused_model/exceptions.py
langchain_fused_model/manager.py
langchain_fused_model/rate_limiter.py
langchain_fused_model/strategy.py
langchain_fused_model/structured_output.py
langchain_fused_model/usage_tracker.py
langchain_fused_model-0.1.1.dist-info/licenses/LICENSE
langchain_fused_model-0.1.1.dist-info/METADATA
langchain_fused_model-0.1.1.dist-info/WHEEL
langchain_fused_model-0.1.1.dist-info/top_level.txt
langchain_fused_model-0.1.1.dist-info/RECORD
