Metadata-Version: 2.4
Name: langchain-fused-model
Version: 0.1.1
Summary: Intelligent routing and management for multiple LangChain ChatModel instances with rate limiting, fallback, and structured output support
Author: LangChain Fused Model Contributors
License: MIT
Project-URL: Homepage, https://github.com/sezer-muhammed/langchain-fused-models
Project-URL: Documentation, https://github.com/sezer-muhammed/langchain-fused-models#readme
Project-URL: Repository, https://github.com/sezer-muhammed/langchain-fused-models
Project-URL: Issues, https://github.com/sezer-muhammed/langchain-fused-models/issues
Keywords: langchain,llm,chatmodel,routing,rate-limiting,fallback
Classifier: Development Status :: 3 - Alpha
Classifier: Intended Audience :: Developers
Classifier: License :: OSI Approved :: MIT License
Classifier: Programming Language :: Python :: 3
Classifier: Programming Language :: Python :: 3.8
Classifier: Programming Language :: Python :: 3.9
Classifier: Programming Language :: Python :: 3.10
Classifier: Programming Language :: Python :: 3.11
Classifier: Programming Language :: Python :: 3.12
Classifier: Topic :: Software Development :: Libraries :: Python Modules
Classifier: Topic :: Scientific/Engineering :: Artificial Intelligence
Requires-Python: >=3.8
License-File: LICENSE
Requires-Dist: langchain>=0.1.0
Requires-Dist: langchain-core>=0.1.0
Requires-Dist: pydantic>=2.0.0
Provides-Extra: dev
Requires-Dist: pytest>=7.0.0; extra == "dev"
Requires-Dist: pytest-asyncio>=0.21.0; extra == "dev"
Requires-Dist: pytest-cov>=4.0.0; extra == "dev"
Requires-Dist: ruff>=0.1.0; extra == "dev"
Requires-Dist: mypy>=1.0.0; extra == "dev"
Dynamic: license-file
